rmw_test_fixture/_dummy.cpython-310-x86_64-linux-gnu.so
ros_rmw_test_fixture-0.14.5.data/data/include/rmw_test_fixture/rmw_test_fixture/rmw_test_fixture.h
ros_rmw_test_fixture-0.14.5.data/data/include/rmw_test_fixture/rmw_test_fixture/visibility_control.h
ros_rmw_test_fixture-0.14.5.data/data/share/ament_index/resource_index/package_run_dependencies/rmw_test_fixture
ros_rmw_test_fixture-0.14.5.data/data/share/ament_index/resource_index/packages/rmw_test_fixture
ros_rmw_test_fixture-0.14.5.data/data/share/ament_index/resource_index/parent_prefix_path/rmw_test_fixture
ros_rmw_test_fixture-0.14.5.data/data/share/rmw_test_fixture/local_setup.bash
ros_rmw_test_fixture-0.14.5.data/data/share/rmw_test_fixture/local_setup.dsv
ros_rmw_test_fixture-0.14.5.data/data/share/rmw_test_fixture/local_setup.sh
ros_rmw_test_fixture-0.14.5.data/data/share/rmw_test_fixture/local_setup.zsh
ros_rmw_test_fixture-0.14.5.data/data/share/rmw_test_fixture/package.dsv
ros_rmw_test_fixture-0.14.5.data/data/share/rmw_test_fixture/package.xml
ros_rmw_test_fixture-0.14.5.data/data/share/rmw_test_fixture/cmake/ament_cmake_export_dependencies-extras.cmake
ros_rmw_test_fixture-0.14.5.data/data/share/rmw_test_fixture/cmake/ament_cmake_export_targets-extras.cmake
ros_rmw_test_fixture-0.14.5.data/data/share/rmw_test_fixture/cmake/rmw_test_fixtureConfig-version.cmake
ros_rmw_test_fixture-0.14.5.data/data/share/rmw_test_fixture/cmake/rmw_test_fixtureConfig.cmake
ros_rmw_test_fixture-0.14.5.data/data/share/rmw_test_fixture/cmake/rmw_test_fixtureExport.cmake
ros_rmw_test_fixture-0.14.5.data/data/share/rmw_test_fixture/environment/ament_prefix_path.dsv
ros_rmw_test_fixture-0.14.5.data/data/share/rmw_test_fixture/environment/ament_prefix_path.sh
ros_rmw_test_fixture-0.14.5.data/data/share/rmw_test_fixture/environment/path.dsv
ros_rmw_test_fixture-0.14.5.data/data/share/rmw_test_fixture/environment/path.sh
ros_rmw_test_fixture-0.14.5.dist-info/METADATA
ros_rmw_test_fixture-0.14.5.dist-info/WHEEL
ros_rmw_test_fixture-0.14.5.dist-info/top_level.txt
ros_rmw_test_fixture-0.14.5.dist-info/RECORD
