Metadata-Version: 2.4
Name: ros-rmw-test-fixture
Version: 0.14.5
Summary: Wheel for the rmw_test_fixture (ros-rmw-test-fixture) ROS 2 package.
Requires-Dist: ros-rmw~=7.8.2
Dynamic: description
Dynamic: description-content-type
Dynamic: requires-dist
Dynamic: summary
